pyspreadsheet/Spreadsheet.py
pyspreadsheet/__init__.py
pyspreadsheet/core/__init__.py
pyspreadsheet/core/manage_sheet.py
pyspreadsheet/core/read.py
pyspreadsheet/core/tool.py
pyspreadsheet/core/write.py
pyspreadsheet-0.2.13.dist-info/LICENSE
pyspreadsheet-0.2.13.dist-info/METADATA
pyspreadsheet-0.2.13.dist-info/WHEEL
pyspreadsheet-0.2.13.dist-info/top_level.txt
pyspreadsheet-0.2.13.dist-info/RECORD
