Metadata-Version: 2.1
Name: pyspreadsheet
Version: 0.2.13
Summary: Easily send data to Google Sheets
Home-page: https://github.com/dacker-team/pyspreadsheet
Author: Dacker
Author-email: hello@dacker.co
License: UNKNOWN
Keywords: send data google spreadsheet sheets easy
Platform: UNKNOWN
Requires-Python: >=3
Requires-Dist: googleauthentication (>=0.0.10)
Requires-Dist: dbstream (>=0.1.2)
Requires-Dist: google-api-python-client (>=1.6.6)
Requires-Dist: pygsheets (>=2.0.2)
Requires-Dist: pyyaml (>=5.3.1)
Requires-Dist: google-auth (>=0.4.8)
Requires-Dist: jinja2 (>=2.11.2)
